{"mc":{
	"body001_1_2c":{
		"frameRate":15,
		"frames":[
			{"res":"020023","x":-28,"y":-89},
			{"res":"020024","x":-24,"y":-90},
			{"res":"020025","x":-25,"y":-109},
			{"res":"020026","x":-30,"y":-109},
			{"res":"020027","x":-31,"y":-109},
			{"res":"020028","x":-30,"y":-88},
			{"res":"600016","x":-29,"y":-86}

		]
}},
"res":{
	"020023":{"x":0,"y":0,"w":53,"h":100},
	"020024":{"x":53,"y":0,"w":61,"h":101},
	"020025":{"x":114,"y":0,"w":45,"h":120},
	"020026":{"x":159,"y":0,"w":50,"h":120},
	"020027":{"x":209,"y":0,"w":51,"h":120},
	"020028":{"x":260,"y":0,"w":74,"h":99},
	"600016":{"x":334,"y":0,"w":62,"h":98}

}}